plot4d/__init__.py
plot4d/plotter.py
plot4d/.ipynb_checkpoints/plotter-checkpoint.py
plot4d-0.1.2.dist-info/METADATA
plot4d-0.1.2.dist-info/WHEEL
plot4d-0.1.2.dist-info/licenses/LICENSE
plot4d-0.1.2.dist-info/RECORD
