Metadata-Version: 2.1
Name: plot4d
Version: 0.1.2
Summary: A simple package that helps plot arbitrary 4d functions. 
Project-URL: Homepage, https://github.com/yubinhu/plot4d
Project-URL: Bug Tracker, https://github.com/yubinhu/plot4d/issues
Author-email: Harvey Hu <harvey_hu@berkeley.edu>
License-File: LICENSE
Classifier: License :: OSI Approved :: MIT License
Classifier: Operating System :: OS Independent
Classifier: Programming Language :: Python :: 3
Requires-Python: >=3.7
Requires-Dist: dataclasses
Requires-Dist: imageio
Requires-Dist: matplotlib
Requires-Dist: numpy
